novadl/__init__.py
novadl/__main__.py
novadl/downloader.py
novadl-1.0.1.dist-info/licenses/LICENSE
novadl-1.0.1.dist-info/METADATA
novadl-1.0.1.dist-info/WHEEL
novadl-1.0.1.dist-info/entry_points.txt
novadl-1.0.1.dist-info/top_level.txt
novadl-1.0.1.dist-info/RECORD
