Metadata-Version: 2.4
Name: novadl
Version: 1.0.1
Summary: A beautiful TUI for downloading videos and audio
Home-page: https://github.com/ShovonSheikh
Author: MD. Shahariar Ahmmed Shovon
Author-email: "MD. Shahariar Ahmmed Shovon" <shovonali885@gmail.com>
License: MIT
Project-URL: Homepage, https://github.com/ShovonSheikh
Classifier: Development Status :: 4 - Beta
Classifier: Intended Audience :: End Users/Desktop
Classifier: Topic :: Multimedia :: Video
Classifier: License :: OSI Approved :: MIT License
Classifier: Programming Language :: Python :: 3
Requires-Python: >=3.8
License-File: LICENSE
Requires-Dist: yt-dlp
Requires-Dist: textual
Requires-Dist: ffmpeg
Dynamic: author
Dynamic: home-page
Dynamic: license-file
Dynamic: requires-python
